calculator/BalanceCalculator.py
calculator/CurrencyConverter.py
calculator/__init__.py
calculator/helpers.py
calculator/tests/BalanceCalculator_test.py
calculator/tests/__init__.py
calculator/tests/computed_notification_test.py
calculator/tests/event_store_test.py
calculator/tests/helpers.py
cryptomodel/__init__.py
cryptomodel/channel_type.py
cryptomodel/coinmarket.py
cryptomodel/computed_notification.py
cryptomodel/config.py
cryptomodel/cryptomodel.py
cryptomodel/cryptostore.py
cryptomodel/cryptostore_expressions.py
cryptomodel/cryptostore_symbol_value.py
cryptomodel/event_store.py
cryptomodel/fixer.py
cryptomodel/helpers.py
cryptomodel/notification_type.py
cryptomodel/operations.py
cryptomodel/order_types.py
cryptomodel/readonly.py
cryptomodel/sent_notification.py
cryptomodel/transaction_types.py
tests/__init__.py
cryptomodel_athanikos-2.6.7.dist-info/LICENSE
cryptomodel_athanikos-2.6.7.dist-info/METADATA
cryptomodel_athanikos-2.6.7.dist-info/WHEEL
cryptomodel_athanikos-2.6.7.dist-info/top_level.txt
cryptomodel_athanikos-2.6.7.dist-info/RECORD
