Metadata-Version: 2.1
Name: cryptomodel-athanikos
Version: 2.6.7
Summary: Model for CryptoStore and CoinMarketCap Collections for Mongo db
Home-page: UNKNOWN
Author: Nikos Athanasakis
Author-email: athanikos@gmail.com
License: MIT License
Platform: UNKNOWN
Classifier: Development Status :: 1 - Planning
Classifier: License :: OSI Approved :: MIT License
Classifier: Operating System :: OS Independent
